gptf/__init__.py
gptf/distributed.py
gptf/gpr.py
gptf/core/__init__.py
gptf/core/densities.py
gptf/core/kernels.py
gptf/core/likelihoods.py
gptf/core/meanfunctions.py
gptf/core/models.py
gptf/core/params.py
gptf/core/tfhacks.py
gptf/core/transforms.py
gptf/core/trees.py
gptf/core/utils.py
gptf/core/wrappedtf.py
gptf-1.1.5.dist-info/DESCRIPTION.rst
gptf-1.1.5.dist-info/METADATA
gptf-1.1.5.dist-info/RECORD
gptf-1.1.5.dist-info/WHEEL
gptf-1.1.5.dist-info/metadata.json
gptf-1.1.5.dist-info/top_level.txt
