Metadata-Version: 2.0
Name: gptf
Version: 1.1.5
Summary: Distributed GPs using TensorFlow.
Home-page: https://github.com/ICL-SML/gptf
Author: Blaine Rogers
Author-email: br1314@ic.ac.uk
License: UNKNOWN
Platform: UNKNOWN
Classifier: Natural Language :: English
Classifier: Programming Language :: Python :: 2.7
Classifier: Programming Language :: Python :: 3.4
Classifier: Programming Language :: Python :: 3.5
Classifier: Programming Language :: Python :: 3.6
Classifier: Topic :: Scientific/Engineering :: Artificial Intelligence
Requires-Dist: future (>=0.15)
Requires-Dist: numpy
Requires-Dist: overrides (>=1.7)
Requires-Dist: scipy
Requires-Dist: tensorflow (>=1.0)
